clusterkit/__init__.py
clusterkit-0.0.1.dist-info/LICENSE
clusterkit-0.0.1.dist-info/WHEEL
clusterkit-0.0.1.dist-info/METADATA
clusterkit-0.0.1.dist-info/RECORD
