Metadata-Version: 2.3
Name: clusterkit
Version: 0.0.1
Summary: A Python package for cluster analysis and visualization.
Author-email: Malte Kuehl <malte.kuehl@clin.au.dk>
Classifier: License :: OSI Approved :: GNU General Public License v3 or later (GPLv3+)
Project-URL: Home, https://github.com/complextissue/clusterkit/
